textbin/__init__.py
textbin/textbin.py
textbin-0.0.1.dist-info/LICENSE
textbin-0.0.1.dist-info/METADATA
textbin-0.0.1.dist-info/WHEEL
textbin-0.0.1.dist-info/top_level.txt
textbin-0.0.1.dist-info/RECORD
