Metadata-Version: 2.1
Name: textbin
Version: 0.0.1
Summary: textbin packge
Author: Comon (Collins Omondi)
Author-email: <comon928@gmail.com>
Keywords: binary,text
Classifier: Development Status :: 1 - Planning
Classifier: Intended Audience :: Developers
Classifier: Programming Language :: Python :: 3
Classifier: Operating System :: Unix
Classifier: Operating System :: MacOS :: MacOS X
Classifier: Operating System :: Microsoft :: Windows
License-File: LICENSE
